{
    "sitemap_count":  350,
    "crawled_pages":  324,
    "orphan_count":  46,
    "orphan_groups":  [
                          {
                              "type":  "taxonomy-detail",
                              "count":  41
                          },
                          {
                              "type":  "page",
                              "count":  4
                          },
                          {
                              "type":  "model",
                              "count":  1
                          }
                      ],
    "orphans":  [
                    {
                        "url":  "https://khimki-dev.krasnodar-night.com/features/vip",
                        "type":  "taxonomy-detail"
                    },
                    {
                        "url":  "https://khimki-dev.krasnodar-night.com/features/proverennyye",
                        "type":  "taxonomy-detail"
                    },
                    {
                        "url":  "https://khimki-dev.krasnodar-night.com/hair-color/blondinka",
                        "type":  "taxonomy-detail"
                    },
                    {
                        "url":  "https://khimki-dev.krasnodar-night.com/hair-color/bryunetka",
                        "type":  "taxonomy-detail"
                    },
                    {
                        "url":  "https://khimki-dev.krasnodar-night.com/hair-color/rusyye",
                        "type":  "taxonomy-detail"
                    },
                    {
                        "url":  "https://khimki-dev.krasnodar-night.com/hair-color/ryzhaya",
                        "type":  "taxonomy-detail"
                    },
                    {
                        "url":  "https://khimki-dev.krasnodar-night.com/hair-color/shatenka",
                        "type":  "taxonomy-detail"
                    },
                    {
                        "url":  "https://khimki-dev.krasnodar-night.com/aye-color/goluboy",
                        "type":  "taxonomy-detail"
                    },
                    {
                        "url":  "https://khimki-dev.krasnodar-night.com/aye-color/zelonyy",
                        "type":  "taxonomy-detail"
                    },
                    {
                        "url":  "https://khimki-dev.krasnodar-night.com/aye-color/kariy",
                        "type":  "taxonomy-detail"
                    },
                    {
                        "url":  "https://khimki-dev.krasnodar-night.com/aye-color/seryy",
                        "type":  "taxonomy-detail"
                    },
                    {
                        "url":  "https://khimki-dev.krasnodar-night.com/nationalities/aziatka",
                        "type":  "taxonomy-detail"
                    },
                    {
                        "url":  "https://khimki-dev.krasnodar-night.com/nationalities/kazashka",
                        "type":  "taxonomy-detail"
                    },
                    {
                        "url":  "https://khimki-dev.krasnodar-night.com/nationalities/russkaya",
                        "type":  "taxonomy-detail"
                    },
                    {
                        "url":  "https://khimki-dev.krasnodar-night.com/nationalities/tatarka",
                        "type":  "taxonomy-detail"
                    },
                    {
                        "url":  "https://khimki-dev.krasnodar-night.com/nationalities/uzbechka",
                        "type":  "taxonomy-detail"
                    },
                    {
                        "url":  "https://khimki-dev.krasnodar-night.com/bust-size/1",
                        "type":  "taxonomy-detail"
                    },
                    {
                        "url":  "https://khimki-dev.krasnodar-night.com/bust-size/2",
                        "type":  "taxonomy-detail"
                    },
                    {
                        "url":  "https://khimki-dev.krasnodar-night.com/bust-size/3",
                        "type":  "taxonomy-detail"
                    },
                    {
                        "url":  "https://khimki-dev.krasnodar-night.com/bust-size/4",
                        "type":  "taxonomy-detail"
                    },
                    {
                        "url":  "https://khimki-dev.krasnodar-night.com/physique/polnaya",
                        "type":  "taxonomy-detail"
                    },
                    {
                        "url":  "https://khimki-dev.krasnodar-night.com/physique/sportivnaya",
                        "type":  "taxonomy-detail"
                    },
                    {
                        "url":  "https://khimki-dev.krasnodar-night.com/physique/stroynaya",
                        "type":  "taxonomy-detail"
                    },
                    {
                        "url":  "https://khimki-dev.krasnodar-night.com/physique/khudaya",
                        "type":  "taxonomy-detail"
                    },
                    {
                        "url":  "https://khimki-dev.krasnodar-night.com/intimate-haircut/akkuratnaya-strizhka",
                        "type":  "taxonomy-detail"
                    },
                    {
                        "url":  "https://khimki-dev.krasnodar-night.com/intimate-haircut/naturalnaya-strizhka",
                        "type":  "taxonomy-detail"
                    },
                    {
                        "url":  "https://khimki-dev.krasnodar-night.com/intimate-haircut/polnaya-depilyatsiya",
                        "type":  "taxonomy-detail"
                    },
                    {
                        "url":  "https://khimki-dev.krasnodar-night.com/extreme-services/anilingus-delayu",
                        "type":  "taxonomy-detail"
                    },
                    {
                        "url":  "https://khimki-dev.krasnodar-night.com/extreme-services/anilingus-prinimayu",
                        "type":  "taxonomy-detail"
                    },
                    {
                        "url":  "https://khimki-dev.krasnodar-night.com/extreme-services/zolotoy-dozhd-vydacha",
                        "type":  "taxonomy-detail"
                    },
                    {
                        "url":  "https://khimki-dev.krasnodar-night.com/extreme-services/zolotoy-dozhd-priyem",
                        "type":  "taxonomy-detail"
                    },
                    {
                        "url":  "https://khimki-dev.krasnodar-night.com/extreme-services/strapon",
                        "type":  "taxonomy-detail"
                    },
                    {
                        "url":  "https://khimki-dev.krasnodar-night.com/extreme-services/fisting-analnyy",
                        "type":  "taxonomy-detail"
                    },
                    {
                        "url":  "https://khimki-dev.krasnodar-night.com/extreme-services/fisting-klassicheskiy",
                        "type":  "taxonomy-detail"
                    },
                    {
                        "url":  "https://khimki-dev.krasnodar-night.com/bdsm/bondazh",
                        "type":  "taxonomy-detail"
                    },
                    {
                        "url":  "https://khimki-dev.krasnodar-night.com/bdsm/gospozha",
                        "type":  "taxonomy-detail"
                    },
                    {
                        "url":  "https://khimki-dev.krasnodar-night.com/bdsm/legkaya-dominatsiya",
                        "type":  "taxonomy-detail"
                    },
                    {
                        "url":  "https://khimki-dev.krasnodar-night.com/bdsm/porka",
                        "type":  "taxonomy-detail"
                    },
                    {
                        "url":  "https://khimki-dev.krasnodar-night.com/bdsm/rabynya",
                        "type":  "taxonomy-detail"
                    },
                    {
                        "url":  "https://khimki-dev.krasnodar-night.com/bdsm/trampling",
                        "type":  "taxonomy-detail"
                    },
                    {
                        "url":  "https://khimki-dev.krasnodar-night.com/bdsm/fetish",
                        "type":  "taxonomy-detail"
                    },
                    {
                        "url":  "https://khimki-dev.krasnodar-night.com/model/id-1",
                        "type":  "model"
                    },
                    {
                        "url":  "https://khimki-dev.krasnodar-night.com/bust-size",
                        "type":  "page"
                    },
                    {
                        "url":  "https://khimki-dev.krasnodar-night.com/individualki",
                        "type":  "page"
                    },
                    {
                        "url":  "https://khimki-dev.krasnodar-night.com/bdsm",
                        "type":  "page"
                    },
                    {
                        "url":  "https://khimki-dev.krasnodar-night.com/kontakty",
                        "type":  "page"
                    }
                ],
    "fetch_errors":  [

                     ]
}
